Fiin/FiinDataHistorical.py
Fiin/FiinDataHistorical.pyi
Fiin/FiinIndicator.py
Fiin/FiinIndicator.pyi
Fiin/FiinSession.py
Fiin/FiinSession.pyi
Fiin/HistoricalReturnData.py
Fiin/HistoricalReturnData.pyi
Fiin/RealTimeReturnData.py
Fiin/RealTimeReturnData.pyi
Fiin/SubscribeForRealTime.py
Fiin/SubscribeForRealTime.pyi
Fiin/__init__.py
Fiin/pyarmor_runtime_000000/__init__.py
Fiin/pyarmor_runtime_000000/pyarmor_runtime.pyd
Fiin-0.0.20.dist-info/METADATA
Fiin-0.0.20.dist-info/WHEEL
Fiin-0.0.20.dist-info/top_level.txt
Fiin-0.0.20.dist-info/RECORD
